iCof4BD_Spark/__init__.py
iCof4BD_Spark/generate_template.py
iCof4BD_Spark/generate_xml.py
iCof4BD_Spark/log_analysis.py
iCof4BD_Spark/start_generate.py
iCof4BD_Spark/web_crawl.py
iCof4BD_Spark-0.1.1.dist-info/METADATA
iCof4BD_Spark-0.1.1.dist-info/WHEEL
iCof4BD_Spark-0.1.1.dist-info/top_level.txt
iCof4BD_Spark-0.1.1.dist-info/RECORD
