Metadata-Version: 2.1
Name: iCof4BD-Spark
Version: 0.1.1
Summary: For iCof4BD_Spark
Home-page: UNKNOWN
Author: zhou yan
Author-email: yan2.zhou@intel.com
License: Apache
Platform: UNKNOWN
